src/__init__.py
src/zero_init.py
zero_init/__init__.py
zero_init/zero_init.py
zero_init-0.3.dist-info/METADATA
zero_init-0.3.dist-info/WHEEL
zero_init-0.3.dist-info/top_level.txt
zero_init-0.3.dist-info/RECORD
